smol_format/__init__.py
smol_format/core.py
smol_format/migrate.py
smol_format/storage.py
smol_format-0.1.2.dist-info/METADATA
smol_format-0.1.2.dist-info/WHEEL
smol_format-0.1.2.dist-info/licenses/LICENSE
smol_format-0.1.2.dist-info/RECORD
