Metadata-Version: 2.4
Name: smol-format
Version: 0.1.2
Summary: A high-density data storage system for efficient encoding and decoding of structured data, with special support for large rational numbers
Project-URL: Homepage, https://github.com/smol-data/smol-format
Author-email: Joshua Small <small.joshua@gmail.com>
License-Expression: MIT
License-File: LICENSE
Keywords: compression,data-storage,json,rational-numbers,zstandard
Classifier: Development Status :: 3 - Alpha
Classifier: Intended Audience :: Science/Research
Classifier: License :: OSI Approved :: MIT License
Classifier: Programming Language :: Python :: 3
Classifier: Programming Language :: Python :: 3.8
Classifier: Programming Language :: Python :: 3.9
Classifier: Programming Language :: Python :: 3.10
Classifier: Programming Language :: Python :: 3.11
Classifier: Topic :: Database :: Database Engines/Servers
Classifier: Topic :: Scientific/Engineering :: Mathematics
Requires-Python: >=3.8
Requires-Dist: pydantic>=2.0.0
Requires-Dist: typing-extensions>=4.0.0
Requires-Dist: zstandard>=0.21.0
Provides-Extra: dev
Requires-Dist: black>=23.0.0; extra == 'dev'
Requires-Dist: flake8>=6.0.0; extra == 'dev'
Requires-Dist: isort>=5.0.0; extra == 'dev'
Requires-Dist: mypy>=1.0.0; extra == 'dev'
Requires-Dist: pytest-cov>=4.0.0; extra == 'dev'
Requires-Dist: pytest>=7.0.0; extra == 'dev'
